{
    "swagger": "2.0",
    "info": {
        "description": "API for managing and querying time series data from IoT sensors\n\nThis API allows you to upload CSV files containing time series data,\nquery the data with time range filters, and manage datasources.\n\nSupported timestamp formats: ISO8601, RFC3339, Unix timestamps (seconds/milliseconds), Julian Day",
        "title": "IoT Data Sandbox API",
        "termsOfService": "http://swagger.io/terms/",
        "contact": {
            "name": "API Support"
        },
        "license": {
            "name": "MIT"
        },
        "version": "1.0"
    },
    "host": "localhost:8080",
    "basePath": "/",
    "paths": {
        "/api/datasources": {
            "get": {
                "description": "Get a list of all registered datasources with their metadata",
                "produces": [
                    "application/json"
                ],
                "tags": [
                    "datasources"
                ],
                "summary": "List all datasources",
                "responses": {
                    "200": {
                        "description": "OK",
                        "schema": {
                            "$ref": "#/definitions/api.DataSourceListResponse"
                        }
                    },
                    "500": {
                        "description": "Internal Server Error",
                        "schema": {
                            "$ref": "#/definitions/api.ErrorResponse"
                        }
                    }
                }
            },
            "post": {
                "description": "Upload a CSV file containing time series data. The CSV must have 'timestamp' and 'value' columns. Supports various timestamp formats (ISO8601, Unix, Julian Day).",
                "consumes": [
                    "multipart/form-data"
                ],
                "produces": [
                    "application/json"
                ],
                "tags": [
                    "datasources"
                ],
                "summary": "Upload a CSV datasource",
                "parameters": [
                    {
                        "type": "file",
                        "description": "CSV file to upload",
                        "name": "file",
                        "in": "formData",
                        "required": true
                    },
                    {
                        "type": "string",
                        "description": "Name for the datasource (defaults to filename)",
                        "name": "name",
                        "in": "formData"
                    }
                ],
                "responses": {
                    "201": {
                        "description": "Created",
                        "schema": {
                            "$ref": "#/definitions/api.UploadResponse"
                        }
                    },
                    "400": {
                        "description": "Bad Request",
                        "schema": {
                            "$ref": "#/definitions/api.ErrorResponse"
                        }
                    },
                    "500": {
                        "description": "Internal Server Error",
                        "schema": {
                            "$ref": "#/definitions/api.ErrorResponse"
                        }
                    }
                }
            }
        },
        "/api/datasources/{id}": {
            "get": {
                "description": "Get metadata for a specific datasource by ID",
                "produces": [
                    "application/json"
                ],
                "tags": [
                    "datasources"
                ],
                "summary": "Get datasource metadata",
                "parameters": [
                    {
                        "type": "integer",
                        "description": "Datasource ID",
                        "name": "id",
                        "in": "path",
                        "required": true
                    }
                ],
                "responses": {
                    "200": {
                        "description": "OK",
                        "schema": {
                            "$ref": "#/definitions/api.DataSourceMetadata"
                        }
                    },
                    "400": {
                        "description": "Bad Request",
                        "schema": {
                            "$ref": "#/definitions/api.ErrorResponse"
                        }
                    },
                    "404": {
                        "description": "Not Found",
                        "schema": {
                            "$ref": "#/definitions/api.ErrorResponse"
                        }
                    }
                }
            },
            "delete": {
                "description": "Delete a datasource and its associated CSV file",
                "tags": [
                    "datasources"
                ],
                "summary": "Delete a datasource",
                "parameters": [
                    {
                        "type": "integer",
                        "description": "Datasource ID",
                        "name": "id",
                        "in": "path",
                        "required": true
                    }
                ],
                "responses": {
                    "204": {
                        "description": "No Content"
                    },
                    "400": {
                        "description": "Bad Request",
                        "schema": {
                            "$ref": "#/definitions/api.ErrorResponse"
                        }
                    },
                    "404": {
                        "description": "Not Found",
                        "schema": {
                            "$ref": "#/definitions/api.ErrorResponse"
                        }
                    },
                    "500": {
                        "description": "Internal Server Error",
                        "schema": {
                            "$ref": "#/definitions/api.ErrorResponse"
                        }
                    }
                }
            }
        },
        "/api/datasources/{id}/data": {
            "get": {
                "description": "Query time series data from a datasource with optional time range filtering",
                "produces": [
                    "application/json"
                ],
                "tags": [
                    "datasources"
                ],
                "summary": "Query time series data",
                "parameters": [
                    {
                        "type": "integer",
                        "description": "Datasource ID",
                        "name": "id",
                        "in": "path",
                        "required": true
                    },
                    {
                        "type": "string",
                        "description": "Start time in RFC3339 format (e.g., 2024-01-01T00:00:00Z)",
                        "name": "start_time",
                        "in": "query"
                    },
                    {
                        "type": "string",
                        "description": "End time in RFC3339 format (e.g., 2024-01-01T23:59:59Z)",
                        "name": "end_time",
                        "in": "query"
                    }
                ],
                "responses": {
                    "200": {
                        "description": "OK",
                        "schema": {
                            "$ref": "#/definitions/api.DataQueryResponse"
                        }
                    },
                    "400": {
                        "description": "Bad Request",
                        "schema": {
                            "$ref": "#/definitions/api.ErrorResponse"
                        }
                    },
                    "404": {
                        "description": "Not Found",
                        "schema": {
                            "$ref": "#/definitions/api.ErrorResponse"
                        }
                    },
                    "500": {
                        "description": "Internal Server Error",
                        "schema": {
                            "$ref": "#/definitions/api.ErrorResponse"
                        }
                    }
                }
            }
        }
    },
    "definitions": {
        "api.DataPoint": {
            "type": "object",
            "properties": {
                "timestamp": {
                    "type": "string"
                },
                "value": {
                    "type": "number"
                }
            }
        },
        "api.DataQueryResponse": {
            "type": "object",
            "properties": {
                "data": {
                    "type": "array",
                    "items": {
                        "$ref": "#/definitions/api.DataPoint"
                    }
                },
                "end_time": {
                    "type": "string"
                },
                "row_count": {
                    "type": "integer"
                },
                "start_time": {
                    "type": "string"
                }
            }
        },
        "api.DataSourceListResponse": {
            "type": "object",
            "properties": {
                "data_sources": {
                    "type": "array",
                    "items": {
                        "$ref": "#/definitions/api.DataSourceMetadata"
                    }
                }
            }
        },
        "api.DataSourceMetadata": {
            "type": "object",
            "properties": {
                "data_source_id": {
                    "type": "integer"
                },
                "end_time": {
                    "type": "string"
                },
                "name": {
                    "type": "string"
                },
                "row_count": {
                    "type": "integer"
                },
                "start_time": {
                    "type": "string"
                },
                "type": {
                    "type": "string"
                },
                "when_created": {
                    "type": "string"
                }
            }
        },
        "api.ErrorResponse": {
            "type": "object",
            "properties": {
                "error": {
                    "type": "string"
                }
            }
        },
        "api.UploadResponse": {
            "type": "object",
            "properties": {
                "data_source_id": {
                    "type": "integer"
                },
                "end_time": {
                    "type": "string"
                },
                "name": {
                    "type": "string"
                },
                "row_count": {
                    "type": "integer"
                },
                "start_time": {
                    "type": "string"
                },
                "when_created": {
                    "type": "string"
                }
            }
        }
    }
}